{
  "Top": "hardware_encoding",
  "RtlTop": "hardware_encoding",
  "RtlPrefix": "",
  "RtlSubPrefix": "hardware_encoding_",
  "SourceLanguage": "cpp",
  "HostMachineBits": "64",
  "FunctionProtocol": "ap_ctrl_chain",
  "ResetStyle": "control",
  "Target": {
    "Family": "zynquplus",
    "Device": "xczu3eg",
    "Package": "-sbva484",
    "Speed": "-1-i",
    "Triple": "fpga64-xilinx-none"
  },
  "Args": {
    "s1": {
      "index": "0",
      "direction": "inout",
      "srcType": "unsigned char*",
      "srcSize": "8",
      "hwRefs": [
        {
          "type": "interface",
          "interface": "m_axi_gmem",
          "name": "",
          "usage": "data",
          "direction": "out"
        },
        {
          "type": "register",
          "interface": "s_axi_control",
          "name": "s1_1",
          "usage": "address",
          "direction": "in"
        },
        {
          "type": "register",
          "interface": "s_axi_control",
          "name": "s1_2",
          "usage": "address",
          "direction": "in"
        }
      ]
    },
    "output": {
      "index": "1",
      "direction": "inout",
      "srcType": "unsigned char*",
      "srcSize": "8",
      "hwRefs": [
        {
          "type": "interface",
          "interface": "m_axi_gmem",
          "name": "",
          "usage": "data",
          "direction": "out"
        },
        {
          "type": "register",
          "interface": "s_axi_control",
          "name": "output_r_1",
          "usage": "address",
          "direction": "in"
        },
        {
          "type": "register",
          "interface": "s_axi_control",
          "name": "output_r_2",
          "usage": "address",
          "direction": "in"
        }
      ]
    },
    "size": {
      "index": "2",
      "direction": "inout",
      "srcType": "int&",
      "srcSize": "32",
      "hwRefs": [{
          "type": "register",
          "interface": "s_axi_control",
          "name": "size",
          "usage": "data",
          "direction": "out"
        }]
    },
    "len": {
      "index": "3",
      "direction": "in",
      "srcType": "int",
      "srcSize": "32",
      "hwRefs": [{
          "type": "register",
          "interface": "s_axi_control",
          "name": "len",
          "usage": "data",
          "direction": "in"
        }]
    }
  },
  "HlsSolution": {
    "FlowTarget": "vitis",
    "ConfigTcl": [
      "config_interface -default_interface=kernel",
      "config_interface -m_axi_alignment_byte_size=64",
      "config_interface -m_axi_latency=64",
      "config_interface -m_axi_max_widen_bitwidth=512",
      "config_interface -m_axi_offset=slave",
      "config_rtl -register_reset_num=3"
    ],
    "DirectiveTcl": [
      "set_directive_top hardware_encoding -name hardware_encoding",
      "set_directive_top hardware_encoding -name hardware_encoding"
    ],
    "ProfileOption": "0",
    "ProfileType": "none",
    "KernelName": "hardware_encoding"
  },
  "ClockInfo": {
    "ClockName": "ap_clk",
    "ClockPeriod": "6.667",
    "Uncertainty": "1.80009",
    "IsCombinational": "0",
    "II": "x",
    "Latency": "undef"
  },
  "Xdc": {"OocClocks": ["create_clock -name ap_clk -period 6.667 [get_ports ap_clk]"]},
  "Ipx": {
    "Vendor": "xilinx.com",
    "Library": "hls",
    "Name": "hardware_encoding",
    "Version": "1.0",
    "DisplayName": "Hardware_encoding",
    "Revision": "",
    "Description": "An IP generated by Vitis HLS",
    "Taxonomy": "\/VITIS_HLS_IP",
    "AutoFamilySupport": "",
    "ZipFile": "xilinx_com_hls_hardware_encoding_1_0.zip"
  },
  "Files": {
    "CSource": ["..\/..\/Server\/LZW_new.cpp"],
    "Vhdl": [
      "impl\/vhdl\/hardware_encoding_control_s_axi.vhd",
      "impl\/vhdl\/hardware_encoding_gmem_m_axi.vhd",
      "impl\/vhdl\/hardware_encoding_hash_table.vhd",
      "impl\/vhdl\/hardware_encoding_insert.vhd",
      "impl\/vhdl\/hardware_encoding_my_assoc_mem_upper_key_mem.vhd",
      "impl\/vhdl\/hardware_encoding_my_assoc_mem_value.vhd",
      "impl\/vhdl\/hardware_encoding.vhd"
    ],
    "Verilog": [
      "impl\/verilog\/hardware_encoding_control_s_axi.v",
      "impl\/verilog\/hardware_encoding_gmem_m_axi.v",
      "impl\/verilog\/hardware_encoding_hash_table.v",
      "impl\/verilog\/hardware_encoding_insert.v",
      "impl\/verilog\/hardware_encoding_my_assoc_mem_upper_key_mem.v",
      "impl\/verilog\/hardware_encoding_my_assoc_mem_value.v",
      "impl\/verilog\/hardware_encoding.v"
    ],
    "SwDriver": [
      "impl\/misc\/drivers\/hardware_encoding_v1_0\/data\/hardware_encoding.mdd",
      "impl\/misc\/drivers\/hardware_encoding_v1_0\/data\/hardware_encoding.tcl",
      "impl\/misc\/drivers\/hardware_encoding_v1_0\/src\/Makefile",
      "impl\/misc\/drivers\/hardware_encoding_v1_0\/src\/xhardware_encoding.c",
      "impl\/misc\/drivers\/hardware_encoding_v1_0\/src\/xhardware_encoding.h",
      "impl\/misc\/drivers\/hardware_encoding_v1_0\/src\/xhardware_encoding_hw.h",
      "impl\/misc\/drivers\/hardware_encoding_v1_0\/src\/xhardware_encoding_linux.c",
      "impl\/misc\/drivers\/hardware_encoding_v1_0\/src\/xhardware_encoding_sinit.c"
    ],
    "IpMisc": ["impl\/misc\/logo.png"],
    "DesignXml": ".autopilot\/db\/hardware_encoding.design.xml",
    "DebugDir": ".debug",
    "ProtoInst": ["\/mnt\/castor\/seas_home\/c\/chiyuan9\/ese532_final\/project\/final_project\/solution1\/.debug\/hardware_encoding.protoinst"]
  },
  "SubcoreInfo": {
    "HasXpmMemory": false,
    "HasClockedDsp": false,
    "Ip": []
  },
  "Interfaces": {
    "ap_clk": {
      "type": "clock",
      "busTypeName": "clock",
      "mode": "slave",
      "busParams": {
        "ASSOCIATED_BUSIF": "s_axi_control:m_axi_gmem",
        "ASSOCIATED_RESET": "ap_rst_n"
      },
      "portMap": {"ap_clk": "CLK"},
      "ports": ["ap_clk"]
    },
    "ap_rst_n": {
      "type": "reset",
      "busTypeName": "reset",
      "mode": "slave",
      "busParams": {"POLARITY": "ACTIVE_LOW"},
      "portMap": {"ap_rst_n": "RST"},
      "ports": ["ap_rst_n"]
    },
    "interrupt": {
      "type": "interrupt",
      "busTypeName": "interrupt",
      "mode": "master",
      "dataWidth": "1",
      "busParams": {"SENSITIVITY": "LEVEL_HIGH"},
      "portMap": {"interrupt": "INTERRUPT"},
      "ports": ["interrupt"]
    },
    "m_axi_gmem": {
      "type": "axi4full",
      "busTypeName": "aximm",
      "mode": "master",
      "dataWidth": "32",
      "addrWidth": "64",
      "portPrefix": "m_axi_gmem_",
      "paramPrefix": "C_M_AXI_GMEM_",
      "offsetSlaveName": "s_axi_control",
      "preferredUsageValue": "MEMORY",
      "busParams": {
        "NUM_READ_OUTSTANDING": "16",
        "NUM_WRITE_OUTSTANDING": "16",
        "MAX_READ_BURST_LENGTH": "16",
        "MAX_WRITE_BURST_LENGTH": "16",
        "MAX_BURST_LENGTH": "256",
        "PROTOCOL": "AXI4",
        "READ_WRITE_MODE": "READ_WRITE",
        "HAS_BURST": "0",
        "SUPPORTS_NARROW_BURST": "0"
      },
      "ports": [
        "m_axi_gmem_ARADDR",
        "m_axi_gmem_ARBURST",
        "m_axi_gmem_ARCACHE",
        "m_axi_gmem_ARID",
        "m_axi_gmem_ARLEN",
        "m_axi_gmem_ARLOCK",
        "m_axi_gmem_ARPROT",
        "m_axi_gmem_ARQOS",
        "m_axi_gmem_ARREADY",
        "m_axi_gmem_ARREGION",
        "m_axi_gmem_ARSIZE",
        "m_axi_gmem_ARUSER",
        "m_axi_gmem_ARVALID",
        "m_axi_gmem_AWADDR",
        "m_axi_gmem_AWBURST",
        "m_axi_gmem_AWCACHE",
        "m_axi_gmem_AWID",
        "m_axi_gmem_AWLEN",
        "m_axi_gmem_AWLOCK",
        "m_axi_gmem_AWPROT",
        "m_axi_gmem_AWQOS",
        "m_axi_gmem_AWREADY",
        "m_axi_gmem_AWREGION",
        "m_axi_gmem_AWSIZE",
        "m_axi_gmem_AWUSER",
        "m_axi_gmem_AWVALID",
        "m_axi_gmem_BID",
        "m_axi_gmem_BREADY",
        "m_axi_gmem_BRESP",
        "m_axi_gmem_BUSER",
        "m_axi_gmem_BVALID",
        "m_axi_gmem_RDATA",
        "m_axi_gmem_RID",
        "m_axi_gmem_RLAST",
        "m_axi_gmem_RREADY",
        "m_axi_gmem_RRESP",
        "m_axi_gmem_RUSER",
        "m_axi_gmem_RVALID",
        "m_axi_gmem_WDATA",
        "m_axi_gmem_WID",
        "m_axi_gmem_WLAST",
        "m_axi_gmem_WREADY",
        "m_axi_gmem_WSTRB",
        "m_axi_gmem_WUSER",
        "m_axi_gmem_WVALID"
      ],
      "constraints": [
        {
          "constraint_type": "pragma interface",
          "mode": "m_axi",
          "register_option": "0",
          "offset": "slave",
          "latency": "64",
          "num_read_outstanding": "16",
          "num_write_outstanding": "16",
          "max_read_burst_length": "16",
          "max_write_burst_length": "16",
          "max_widen_bitwidth": "512",
          "argName": "s1"
        },
        {
          "constraint_type": "bitwidth",
          "orig_bitwidth": "8",
          "final_bitwidth": "8",
          "argName": "s1"
        }
      ]
    },
    "s_axi_control": {
      "type": "axi4lite",
      "busTypeName": "aximm",
      "mode": "slave",
      "dataWidth": "32",
      "addrWidth": "6",
      "portPrefix": "s_axi_control_",
      "paramPrefix": "C_S_AXI_CONTROL_",
      "offsetMasterName": "m_axi_gmem",
      "ports": [
        "s_axi_control_ARADDR",
        "s_axi_control_ARREADY",
        "s_axi_control_ARVALID",
        "s_axi_control_AWADDR",
        "s_axi_control_AWREADY",
        "s_axi_control_AWVALID",
        "s_axi_control_BREADY",
        "s_axi_control_BRESP",
        "s_axi_control_BVALID",
        "s_axi_control_RDATA",
        "s_axi_control_RREADY",
        "s_axi_control_RRESP",
        "s_axi_control_RVALID",
        "s_axi_control_WDATA",
        "s_axi_control_WREADY",
        "s_axi_control_WSTRB",
        "s_axi_control_WVALID"
      ],
      "registers": [
        {
          "offset": "0x00",
          "name": "CTRL",
          "access": "RW",
          "resetValue": "0x0",
          "description": "Control signals",
          "range": "32",
          "fields": [
            {
              "offset": "0",
              "width": "1",
              "name": "AP_START",
              "access": "RW",
              "resetValue": "0",
              "description": "Control signal Register for 'ap_start'."
            },
            {
              "offset": "1",
              "width": "1",
              "name": "AP_DONE",
              "access": "R",
              "resetValue": "0",
              "description": "Control signal Register for 'ap_done'."
            },
            {
              "offset": "2",
              "width": "1",
              "name": "AP_IDLE",
              "access": "R",
              "resetValue": "0",
              "description": "Control signal Register for 'ap_idle'."
            },
            {
              "offset": "3",
              "width": "1",
              "name": "AP_READY",
              "access": "R",
              "resetValue": "0",
              "description": "Control signal Register for 'ap_ready'."
            },
            {
              "offset": "4",
              "width": "1",
              "name": "AP_CONTINUE",
              "access": "R",
              "resetValue": "0",
              "description": "Control signal Register for 'ap_continue'."
            },
            {
              "offset": "5",
              "width": "2",
              "name": "RESERVED_1",
              "access": "R",
              "resetValue": "0",
              "description": "Reserved.  0s on read."
            },
            {
              "offset": "7",
              "width": "1",
              "name": "AUTO_RESTART",
              "access": "RW",
              "resetValue": "0",
              "description": "Control signal Register for 'auto_restart'."
            },
            {
              "offset": "8",
              "width": "24",
              "name": "RESERVED_2",
              "access": "R",
              "resetValue": "0",
              "description": "Reserved.  0s on read."
            }
          ]
        },
        {
          "offset": "0x04",
          "name": "GIER",
          "access": "RW",
          "resetValue": "0x0",
          "description": "Global Interrupt Enable Register",
          "range": "32",
          "fields": [
            {
              "offset": "0",
              "width": "1",
              "name": "Enable",
              "access": "RW",
              "resetValue": "0",
              "description": "Master enable for the device interrupt output to the system interrupt controller: 0 = Disabled, 1 = Enabled"
            },
            {
              "offset": "1",
              "width": "31",
              "name": "RESERVED",
              "access": "R",
              "resetValue": "0",
              "description": "Reserved.  0s on read."
            }
          ]
        },
        {
          "offset": "0x08",
          "name": "IP_IER",
          "access": "RW",
          "resetValue": "0x0",
          "description": "IP Interrupt Enable Register",
          "range": "32",
          "fields": [
            {
              "offset": "0",
              "width": "1",
              "name": "CHAN0_INT_EN",
              "access": "RW",
              "resetValue": "0",
              "description": "Enable Channel 0 (ap_done) Interrupt.  0 = Disabled, 1 = Enabled."
            },
            {
              "offset": "1",
              "width": "1",
              "name": "CHAN1_INT_EN",
              "access": "RW",
              "resetValue": "0",
              "description": "Enable Channel 1 (ap_ready) Interrupt.  0 = Disabled, 1 = Enabled."
            },
            {
              "offset": "2",
              "width": "30",
              "name": "RESERVED",
              "access": "R",
              "resetValue": "0",
              "description": "Reserved.  0s on read."
            }
          ]
        },
        {
          "offset": "0x0c",
          "name": "IP_ISR",
          "access": "RW",
          "resetValue": "0x0",
          "description": "IP Interrupt Status Register",
          "range": "32",
          "fields": [
            {
              "offset": "0",
              "width": "1",
              "name": "CHAN0_INT_ST",
              "access": "RTOW",
              "resetValue": "0",
              "description": "Channel 0 (ap_done) Interrupt Status. 0 = No Channel 0 input interrupt, 1 = Channel 0 input interrup"
            },
            {
              "offset": "1",
              "width": "1",
              "name": "CHAN1_INT_ST",
              "access": "RTOW",
              "resetValue": "0",
              "description": "Channel 1 (ap_ready) Interrupt Status. 0 = No Channel 1 input interrupt, 1 = Channel 1 input interrup"
            },
            {
              "offset": "2",
              "width": "30",
              "name": "RESERVED",
              "access": "R",
              "resetValue": "0",
              "description": "Reserved.  0s on read."
            }
          ]
        },
        {
          "offset": "0x10",
          "name": "s1_1",
          "access": "W",
          "resetValue": "0x0",
          "description": "Data signal of s1",
          "range": "32",
          "fields": [{
              "offset": "0",
              "width": "32",
              "name": "s1",
              "access": "W",
              "resetValue": "0",
              "description": "Bit 31 to 0 of s1"
            }]
        },
        {
          "offset": "0x14",
          "name": "s1_2",
          "access": "W",
          "resetValue": "0x0",
          "description": "Data signal of s1",
          "range": "32",
          "fields": [{
              "offset": "0",
              "width": "32",
              "name": "s1",
              "access": "W",
              "resetValue": "0",
              "description": "Bit 63 to 32 of s1"
            }]
        },
        {
          "offset": "0x1c",
          "name": "output_r_1",
          "access": "W",
          "resetValue": "0x0",
          "description": "Data signal of output_r",
          "range": "32",
          "fields": [{
              "offset": "0",
              "width": "32",
              "name": "output_r",
              "access": "W",
              "resetValue": "0",
              "description": "Bit 31 to 0 of output_r"
            }]
        },
        {
          "offset": "0x20",
          "name": "output_r_2",
          "access": "W",
          "resetValue": "0x0",
          "description": "Data signal of output_r",
          "range": "32",
          "fields": [{
              "offset": "0",
              "width": "32",
              "name": "output_r",
              "access": "W",
              "resetValue": "0",
              "description": "Bit 63 to 32 of output_r"
            }]
        },
        {
          "offset": "0x28",
          "name": "size",
          "access": "R",
          "resetValue": "0x0",
          "description": "Data signal of size",
          "range": "32",
          "fields": [{
              "offset": "0",
              "width": "32",
              "name": "size",
              "access": "R",
              "resetValue": "0",
              "description": "Bit 31 to 0 of size"
            }]
        },
        {
          "offset": "0x38",
          "name": "len",
          "access": "W",
          "resetValue": "0x0",
          "description": "Data signal of len",
          "range": "32",
          "fields": [{
              "offset": "0",
              "width": "32",
              "name": "len",
              "access": "W",
              "resetValue": "0",
              "description": "Bit 31 to 0 of len"
            }]
        }
      ],
      "constraints": [{
          "constraint_type": "pragma interface",
          "mode": "s_axilite",
          "register_option": "0",
          "offset": "16",
          "argName": "s1"
        }]
    }
  },
  "RtlPorts": {
    "s_axi_control_AWVALID": {
      "dir": "in",
      "width": "1"
    },
    "s_axi_control_AWREADY": {
      "dir": "out",
      "width": "1"
    },
    "s_axi_control_AWADDR": {
      "dir": "in",
      "width": "6"
    },
    "s_axi_control_WVALID": {
      "dir": "in",
      "width": "1"
    },
    "s_axi_control_WREADY": {
      "dir": "out",
      "width": "1"
    },
    "s_axi_control_WDATA": {
      "dir": "in",
      "width": "32"
    },
    "s_axi_control_WSTRB": {
      "dir": "in",
      "width": "4"
    },
    "s_axi_control_ARVALID": {
      "dir": "in",
      "width": "1"
    },
    "s_axi_control_ARREADY": {
      "dir": "out",
      "width": "1"
    },
    "s_axi_control_ARADDR": {
      "dir": "in",
      "width": "6"
    },
    "s_axi_control_RVALID": {
      "dir": "out",
      "width": "1"
    },
    "s_axi_control_RREADY": {
      "dir": "in",
      "width": "1"
    },
    "s_axi_control_RDATA": {
      "dir": "out",
      "width": "32"
    },
    "s_axi_control_RRESP": {
      "dir": "out",
      "width": "2"
    },
    "s_axi_control_BVALID": {
      "dir": "out",
      "width": "1"
    },
    "s_axi_control_BREADY": {
      "dir": "in",
      "width": "1"
    },
    "s_axi_control_BRESP": {
      "dir": "out",
      "width": "2"
    },
    "ap_clk": {
      "dir": "in",
      "width": "1"
    },
    "ap_rst_n": {
      "dir": "in",
      "width": "1"
    },
    "interrupt": {
      "dir": "out",
      "width": "1"
    },
    "m_axi_gmem_AWVALID": {
      "dir": "out",
      "width": "1"
    },
    "m_axi_gmem_AWREADY": {
      "dir": "in",
      "width": "1"
    },
    "m_axi_gmem_AWADDR": {
      "dir": "out",
      "width": "64"
    },
    "m_axi_gmem_AWID": {
      "dir": "out",
      "width": "1",
      "isVector": "true"
    },
    "m_axi_gmem_AWLEN": {
      "dir": "out",
      "width": "8"
    },
    "m_axi_gmem_AWSIZE": {
      "dir": "out",
      "width": "3"
    },
    "m_axi_gmem_AWBURST": {
      "dir": "out",
      "width": "2"
    },
    "m_axi_gmem_AWLOCK": {
      "dir": "out",
      "width": "2"
    },
    "m_axi_gmem_AWCACHE": {
      "dir": "out",
      "width": "4"
    },
    "m_axi_gmem_AWPROT": {
      "dir": "out",
      "width": "3"
    },
    "m_axi_gmem_AWQOS": {
      "dir": "out",
      "width": "4"
    },
    "m_axi_gmem_AWREGION": {
      "dir": "out",
      "width": "4"
    },
    "m_axi_gmem_AWUSER": {
      "dir": "out",
      "width": "1",
      "isVector": "true"
    },
    "m_axi_gmem_WVALID": {
      "dir": "out",
      "width": "1"
    },
    "m_axi_gmem_WREADY": {
      "dir": "in",
      "width": "1"
    },
    "m_axi_gmem_WDATA": {
      "dir": "out",
      "width": "32"
    },
    "m_axi_gmem_WSTRB": {
      "dir": "out",
      "width": "4"
    },
    "m_axi_gmem_WLAST": {
      "dir": "out",
      "width": "1"
    },
    "m_axi_gmem_WID": {
      "dir": "out",
      "width": "1",
      "isVector": "true"
    },
    "m_axi_gmem_WUSER": {
      "dir": "out",
      "width": "1",
      "isVector": "true"
    },
    "m_axi_gmem_ARVALID": {
      "dir": "out",
      "width": "1"
    },
    "m_axi_gmem_ARREADY": {
      "dir": "in",
      "width": "1"
    },
    "m_axi_gmem_ARADDR": {
      "dir": "out",
      "width": "64"
    },
    "m_axi_gmem_ARID": {
      "dir": "out",
      "width": "1",
      "isVector": "true"
    },
    "m_axi_gmem_ARLEN": {
      "dir": "out",
      "width": "8"
    },
    "m_axi_gmem_ARSIZE": {
      "dir": "out",
      "width": "3"
    },
    "m_axi_gmem_ARBURST": {
      "dir": "out",
      "width": "2"
    },
    "m_axi_gmem_ARLOCK": {
      "dir": "out",
      "width": "2"
    },
    "m_axi_gmem_ARCACHE": {
      "dir": "out",
      "width": "4"
    },
    "m_axi_gmem_ARPROT": {
      "dir": "out",
      "width": "3"
    },
    "m_axi_gmem_ARQOS": {
      "dir": "out",
      "width": "4"
    },
    "m_axi_gmem_ARREGION": {
      "dir": "out",
      "width": "4"
    },
    "m_axi_gmem_ARUSER": {
      "dir": "out",
      "width": "1",
      "isVector": "true"
    },
    "m_axi_gmem_RVALID": {
      "dir": "in",
      "width": "1"
    },
    "m_axi_gmem_RREADY": {
      "dir": "out",
      "width": "1"
    },
    "m_axi_gmem_RDATA": {
      "dir": "in",
      "width": "32"
    },
    "m_axi_gmem_RLAST": {
      "dir": "in",
      "width": "1"
    },
    "m_axi_gmem_RID": {
      "dir": "in",
      "width": "1",
      "isVector": "true"
    },
    "m_axi_gmem_RUSER": {
      "dir": "in",
      "width": "1",
      "isVector": "true"
    },
    "m_axi_gmem_RRESP": {
      "dir": "in",
      "width": "2"
    },
    "m_axi_gmem_BVALID": {
      "dir": "in",
      "width": "1"
    },
    "m_axi_gmem_BREADY": {
      "dir": "out",
      "width": "1"
    },
    "m_axi_gmem_BRESP": {
      "dir": "in",
      "width": "2"
    },
    "m_axi_gmem_BID": {
      "dir": "in",
      "width": "1",
      "isVector": "true"
    },
    "m_axi_gmem_BUSER": {
      "dir": "in",
      "width": "1",
      "isVector": "true"
    }
  },
  "ModuleInfo": {
    "Hierarchy": {
      "ModuleName": "hardware_encoding",
      "Instances": [{
          "ModuleName": "insert",
          "InstanceName": "grp_insert_fu_2380"
        }]
    },
    "Info": {
      "insert": {
        "FunctionProtocol": "ap_ctrl_hs",
        "isTaskLevelControl": "0",
        "isPipelined": "1",
        "isCombinational": "0",
        "isOneStateSeq": "0"
      },
      "hardware_encoding": {
        "FunctionProtocol": "ap_ctrl_chain",
        "isTaskLevelControl": "0",
        "isPipelined": "0",
        "isCombinational": "0",
        "isOneStateSeq": "0"
      }
    },
    "Metrics": {
      "insert": {
        "Latency": {
          "LatencyBest": "12",
          "LatencyAvg": "12",
          "LatencyWorst": "12",
          "PipelineII": "2",
          "PipelineDepth": "13",
          "PipelineType": "yes"
        },
        "Timing": {
          "Target": "6.67",
          "Uncertainty": "1.80",
          "Estimate": "4.812"
        },
        "Area": {
          "FF": "2380",
          "AVAIL_FF": "141120",
          "UTIL_FF": "1",
          "LUT": "4938",
          "AVAIL_LUT": "70560",
          "UTIL_LUT": "6",
          "BRAM_18K": "0",
          "AVAIL_BRAM": "432",
          "UTIL_BRAM": "0",
          "DSP": "0",
          "AVAIL_DSP": "360",
          "UTIL_DSP": "0",
          "URAM": "0",
          "AVAIL_URAM": "0",
          "UTIL_URAM": "0"
        }
      },
      "hardware_encoding": {
        "Latency": {
          "LatencyBest": "",
          "LatencyAvg": "",
          "LatencyWorst": "",
          "PipelineII": "",
          "PipelineDepth": "",
          "PipelineType": "none"
        },
        "Timing": {
          "Target": "6.67",
          "Uncertainty": "1.80",
          "Estimate": "53.330"
        },
        "Loops": [
          {
            "Name": "VITIS_LOOP_189_1",
            "TripCount": "32768",
            "Latency": "32768",
            "PipelineII": "1",
            "PipelineDepth": "1"
          },
          {
            "Name": "VITIS_LOOP_194_2",
            "TripCount": "512",
            "Latency": "512",
            "PipelineII": "1",
            "PipelineDepth": "1"
          },
          {
            "Name": "VITIS_LOOP_217_4",
            "TripCount": "",
            "Latency": "",
            "PipelineII": "86",
            "PipelineDepth": "154"
          },
          {
            "Name": "VITIS_LOOP_223_5",
            "TripCount": "12",
            "Latency": "81",
            "PipelineII": "1",
            "PipelineDepth": "71"
          }
        ],
        "Area": {
          "BRAM_18K": "68",
          "AVAIL_BRAM": "432",
          "UTIL_BRAM": "15",
          "FF": "9846",
          "AVAIL_FF": "141120",
          "UTIL_FF": "6",
          "LUT": "20736",
          "AVAIL_LUT": "70560",
          "UTIL_LUT": "29",
          "DSP": "0",
          "AVAIL_DSP": "360",
          "UTIL_DSP": "0",
          "URAM": "0",
          "AVAIL_URAM": "0",
          "UTIL_URAM": "0"
        }
      }
    }
  },
  "GenerateBdFiles": "0",
  "GenData": {
    "DataVersion": "0.2",
    "Time": "2023-11-12 20:23:42 EST",
    "ToolName": "vivado_hls",
    "ToolVersion": "2020.2"
  }
}
